katakate/__init__.py
katakate/client.py
katakate-0.0.1.dist-info/licenses/LICENSE
katakate-0.0.1.dist-info/METADATA
katakate-0.0.1.dist-info/WHEEL
katakate-0.0.1.dist-info/top_level.txt
katakate-0.0.1.dist-info/RECORD
