Metadata-Version: 2.4
Name: katakate
Version: 0.0.1
Summary: Katakate Sandbox Management Python SDK
Requires-Python: >=3.8
License-File: LICENSE
Requires-Dist: requests>=2.31.0
Provides-Extra: sdk-async
Requires-Dist: httpx>=0.27.0; extra == "sdk-async"
Dynamic: license-file
Dynamic: provides-extra
Dynamic: requires-dist
Dynamic: requires-python
Dynamic: summary
